microsoft_agents/authentication/msal/__init__.py
microsoft_agents/authentication/msal/msal_auth.py
microsoft_agents/authentication/msal/msal_connection_manager.py
microsoft_agents/authentication/msal/errors/__init__.py
microsoft_agents/authentication/msal/errors/error_resources.py
microsoft_agents_authentication_msal-0.7.0.dist-info/licenses/LICENSE
microsoft_agents_authentication_msal-0.7.0.dist-info/METADATA
microsoft_agents_authentication_msal-0.7.0.dist-info/WHEEL
microsoft_agents_authentication_msal-0.7.0.dist-info/top_level.txt
microsoft_agents_authentication_msal-0.7.0.dist-info/RECORD
