Metadata-Version: 2.4
Name: microsoft-agents-authentication-msal
Version: 0.7.0
Summary: A msal-based authentication library for Microsoft Agents
Author: Microsoft Corporation
License-Expression: MIT
Project-URL: Homepage, https://github.com/microsoft/Agents
Classifier: Programming Language :: Python :: 3
Classifier: Programming Language :: Python :: 3.10
Classifier: Programming Language :: Python :: 3.11
Classifier: Programming Language :: Python :: 3.12
Classifier: Programming Language :: Python :: 3.13
Classifier: Programming Language :: Python :: 3.14
Classifier: Operating System :: OS Independent
Requires-Python: >=3.10
License-File: LICENSE
Requires-Dist: microsoft-agents-hosting-core==0.7.0
Requires-Dist: msal>=1.31.1
Requires-Dist: requests>=2.32.3
Requires-Dist: cryptography>=44.0.0
Dynamic: license-file
Dynamic: requires-dist
